doc/source/conf.py
tests/__init__.py
tests/conftest.py
tests/test_cli.py
tests/test_integration.py
tests/test_models.py
tests/test_services.py
tests/test_settings.py
tests/test_state_access.py
tfmate/__init__.py
tfmate/__main__.py
tfmate/exc.py
tfmate/py.typed
tfmate/settings.py
tfmate/types.py
tfmate/cli/__init__.py
tfmate/cli/analyze_commands.py
tfmate/cli/aws_commands.py
tfmate/cli/main.py
tfmate/cli/terraform_commands.py
tfmate/models/__init__.py
tfmate/models/aws.py
tfmate/models/terraform.py
tfmate/services/__init__.py
tfmate/services/credential_manager.py
tfmate/services/state_detector.py
tfmate/services/terraform_parser.py
tfmate/services/state_access/__init__.py
tfmate/services/state_access/http.py
tfmate/services/state_access/local.py
tfmate/services/state_access/s3.py
tfmate/services/state_access/tfe.py
tfmate-0.2.1.dist-info/licenses/LICENSE.txt
tfmate-0.2.1.dist-info/METADATA
tfmate-0.2.1.dist-info/WHEEL
tfmate-0.2.1.dist-info/entry_points.txt
tfmate-0.2.1.dist-info/top_level.txt
tfmate-0.2.1.dist-info/RECORD
