Metadata-Version: 2.4
Name: tfmate
Version: 0.2.1
Summary: Supporting tools for working with terraform code.
Author-email: Christopher Malek <cmalek@placodermi.org>
Maintainer-email: Christopher Malek <cmalek@placodermi.org>
Project-URL: Source, https://github.com/cmalek/tfmate
Project-URL: Issues, https://github.com/cmalek/tfmate/issues
Keywords: terraform,aws
Classifier: Development Status :: 5 - Production/Stable
Classifier: Intended Audience :: Developers
Classifier: Operating System :: OS Independent
Classifier: Programming Language :: Python
Classifier: Programming Language :: Python :: 3
Classifier: Programming Language :: Python :: 3.10
Classifier: Programming Language :: Python :: 3.11
Classifier: Programming Language :: Python :: 3.12
Classifier: Programming Language :: Python :: 3.13
Requires-Python: >=3.10
License-File: LICENSE.txt
Requires-Dist: boto3>=1.39.14
Requires-Dist: botocore>=1.39.14
Requires-Dist: click>=8.2.1
Requires-Dist: packaging>=25.0
Requires-Dist: pathspec>=0.12.1
Requires-Dist: pydantic>=2.11.7
Requires-Dist: pydantic-settings>=2.10.1
Requires-Dist: python-hcl2>=7.3.1
Requires-Dist: requests>=2.32.4
Requires-Dist: rich>=14.1.0
Dynamic: license-file
